nbrb/__init__.py
nbrb/client.py
nbrb/exceptions.py
nbrb/models.py
nbrb-1.0.0.dist-info/licenses/LICENSE
nbrb-1.0.0.dist-info/METADATA
nbrb-1.0.0.dist-info/WHEEL
nbrb-1.0.0.dist-info/top_level.txt
nbrb-1.0.0.dist-info/RECORD
