Metadata-Version: 2.4
Name: nbrb
Version: 1.0.0
Summary: Курсы валют Национального банка Республики Беларусь
Author-email: Vladimir Nadulich <g240596448@gmail.com>
License-Expression: MIT
Project-URL: Homepage, https://gitlab.com/240596448/nbrb
Project-URL: Documentation, https://gitlab.com/240596448/nbrb/-/blob/master/README.md
Project-URL: Repository, https://gitlab.com/240596448/nbrb
Project-URL: Bug Tracker, https://gitlab.com/240596448/nbrb/-/issues
Keywords: Беларусь,РБ,nbrb,курсы,валюты
Classifier: Development Status :: 5 - Production/Stable
Classifier: Intended Audience :: Developers
Classifier: Programming Language :: Python :: 3
Classifier: Programming Language :: Python :: 3.9
Classifier: Programming Language :: Python :: 3.10
Classifier: Programming Language :: Python :: 3.11
Classifier: Programming Language :: Python :: 3.12
Classifier: Programming Language :: Python :: 3.13
Classifier: Programming Language :: Python :: 3.14
Classifier: Topic :: Office/Business :: Financial
Requires-Python: >=3.9
License-File: LICENSE
Requires-Dist: requests>=2.31
Provides-Extra: dev
Requires-Dist: pytest>=8.0; extra == "dev"
Requires-Dist: pytest-cov>=7.0; extra == "dev"
Dynamic: license-file
